[
  {
    "value": "quickswap",
    "label": "QuickSwap"
  },
  {
    "value": "sushiswap",
    "label": "SushiSwap"
  },
  {
    "value": "apeswap",
    "label": "Apeswap"
  },
  {
    "value": "BANANA",
    "label": "BANANA"
  },
  {
    "value": "CRYSTL",
    "label": "CRYSTL"
  },
  {
    "value": "WATCH",
    "label": "WATCH"
  },
  {
    "value": "DAI",
    "label": "DAI"
  },
  {
    "value": "WOOFY",
    "label": "WOOFY"
  },
  {
    "value": "USDT",
    "label": "USDT"
  },
  {
    "value": "IRON",
    "label": "IRON"
  },
  {
    "value": "USDT",
    "label": "USDT"
  },
  {
    "value": "JDI",
    "label": "JDI"
  },
  {
    "value": "dTOP",
    "label": "dTOP"
  },
  {
    "value": "USDC",
    "label": "USDC"
  },
  {
    "value": "BIFI",
    "label": "BIFI"
  },
  {
    "value": "USDC",
    "label": "USDC"
  },
  {
    "value": "PAUTO",
    "label": "PAUTO"
  },
  {
    "value": "USDC",
    "label": "USDC"
  },
  {
    "value": "ADDY",
    "label": "ADDY"
  },
  {
    "value": "USDC",
    "label": "USDC"
  },
  {
    "value": "USDT",
    "label": "USDT"
  },
  {
    "value": "USDC",
    "label": "USDC"
  },
  {
    "value": "USDT",
    "label": "USDT"
  },
  {
    "value": "USDC",
    "label": "USDC"
  },
  {
    "value": "BNB",
    "label": "BNB"
  },
  {
    "value": "USDC",
    "label": "USDC"
  },
  {
    "value": "DAI",
    "label": "DAI"
  },
  {
    "value": "ABR",
    "label": "ABR"
  },
  {
    "value": "USDC",
    "label": "USDC"
  },
  {
    "value": "USDC",
    "label": "USDC"
  },
  {
    "value": "DAI",
    "label": "DAI"
  },
  {
    "value": "FRAX",
    "label": "FRAX"
  },
  {
    "value": "USDC",
    "label": "USDC"
  },
  {
    "value": "USDC",
    "label": "USDC"
  },
  {
    "value": "INSUR",
    "label": "INSUR"
  },
  {
    "value": "LINK",
    "label": "LINK"
  },
  {
    "value": "LINK",
    "label": "LINK"
  },
  {
    "value": "ARPA",
    "label": "ARPA"
  },
  {
    "value": "IRIS",
    "label": "IRIS"
  },
  {
    "value": "EROWAN",
    "label": "EROWAN"
  },
  {
    "value": "USDC",
    "label": "USDC"
  },
  {
    "value": "SNX",
    "label": "SNX"
  },
  {
    "value": "GRT",
    "label": "GRT"
  },
  {
    "value": "renDOGE",
    "label": "renDOGE"
  },
  {
    "value": "ADDY",
    "label": "ADDY"
  },
  {
    "value": "$ANRX",
    "label": "$ANRX"
  },
  {
    "value": "miMATIC",
    "label": "miMATIC"
  },
  {
    "value": "USDT",
    "label": "USDT"
  },
  {
    "value": "miMATIC",
    "label": "miMATIC"
  },
  {
    "value": "USDC",
    "label": "USDC"
  },
  {
    "value": "ETHA",
    "label": "ETHA"
  },
  {
    "value": "DHT",
    "label": "DHT"
  },
  {
    "value": "renDOGE",
    "label": "renDOGE"
  },
  {
    "value": "MITx",
    "label": "MITx"
  },
  {
    "value": "ODDZ",
    "label": "ODDZ"
  },
  {
    "value": "USDC",
    "label": "USDC"
  },
  {
    "value": "REVV",
    "label": "REVV"
  },
  {
    "value": "USDT",
    "label": "USDT"
  },
  {
    "value": "SOL",
    "label": "SOL"
  },
  {
    "value": "UNI",
    "label": "UNI"
  },
  {
    "value": "WBTC",
    "label": "WBTC"
  },
  {
    "value": "EROWAN",
    "label": "EROWAN"
  },
  {
    "value": "REGEN",
    "label": "REGEN"
  },
  {
    "value": "USDC",
    "label": "USDC"
  },
  {
    "value": "rUSD",
    "label": "rUSD"
  },
  {
    "value": "DPI",
    "label": "DPI"
  },
  {
    "value": "AAVE",
    "label": "AAVE"
  },
  {
    "value": "WFIL",
    "label": "WFIL"
  },
  {
    "value": "AAVE",
    "label": "AAVE"
  },
  {
    "value": "WBTC",
    "label": "WBTC"
  },
  {
    "value": "ibBTC",
    "label": "ibBTC"
  },
  {
    "value": "WBTC",
    "label": "WBTC"
  },
  {
    "value": "WBTC",
    "label": "WBTC"
  },
  {
    "value": "USDC",
    "label": "USDC"
  },
  {
    "value": "DAI",
    "label": "DAI"
  },
  {
    "value": "USDC",
    "label": "USDC"
  },
  {
    "value": "DAI",
    "label": "DAI"
  },
  {
    "value": "DAI",
    "label": "DAI"
  },
  {
    "value": "miMATIC",
    "label": "miMATIC"
  },
  {
    "value": "PICKLE",
    "label": "PICKLE"
  },
  {
    "value": "DAI",
    "label": "DAI"
  },
  {
    "value": "DAI",
    "label": "DAI"
  },
  {
    "value": "WOO",
    "label": "WOO"
  },
  {
    "value": "USDC",
    "label": "USDC"
  },
  {
    "value": "zUSD",
    "label": "zUSD"
  },
  {
    "value": "USDC",
    "label": "USDC"
  },
  {
    "value": "USDC",
    "label": "USDC"
  },
  {
    "value": "WOW",
    "label": "WOW"
  },
  {
    "value": "PolyDoge",
    "label": "PolyDoge"
  },
  {
    "value": "UNI",
    "label": "UNI"
  },
  {
    "value": "EROWAN",
    "label": "EROWAN"
  },
  {
    "value": "XCASH",
    "label": "XCASH"
  },
  {
    "value": "DHV",
    "label": "DHV"
  },
  {
    "value": "EZ",
    "label": "EZ"
  },
  {
    "value": "XED",
    "label": "XED"
  },
  {
    "value": "OOE",
    "label": "OOE"
  },
  {
    "value": "MITx",
    "label": "MITx"
  },
  {
    "value": "TRADE",
    "label": "TRADE"
  },
  {
    "value": "WOW",
    "label": "WOW"
  },
  {
    "value": "MANA",
    "label": "MANA"
  },
  {
    "value": "USDC",
    "label": "USDC"
  },
  {
    "value": "MOONED",
    "label": "MOONED"
  },
  {
    "value": "DATA",
    "label": "DATA"
  },
  {
    "value": "PBR",
    "label": "PBR"
  },
  {
    "value": "USDT",
    "label": "USDT"
  },
  {
    "value": "CNTR",
    "label": "CNTR"
  },
  {
    "value": "GMEE",
    "label": "GMEE"
  },
  {
    "value": "PIXEL",
    "label": "PIXEL"
  },
  {
    "value": "QI",
    "label": "QI"
  },
  {
    "value": "IDLE",
    "label": "IDLE"
  },
  {
    "value": "polyBUNNY",
    "label": "polyBUNNY"
  },
  {
    "value": "renDGB",
    "label": "renDGB"
  },
  {
    "value": "NEXO",
    "label": "NEXO"
  },
  {
    "value": "KOM",
    "label": "KOM"
  },
  {
    "value": "FRAX",
    "label": "FRAX"
  },
  {
    "value": "FXS",
    "label": "FXS"
  },
  {
    "value": "SHIB",
    "label": "SHIB"
  },
  {
    "value": "USDC",
    "label": "USDC"
  },
  {
    "value": "TUSD",
    "label": "TUSD"
  },
  {
    "value": "ODDZ",
    "label": "ODDZ"
  },
  {
    "value": "WBTC",
    "label": "WBTC"
  },
  {
    "value": "USDC",
    "label": "USDC"
  },
  {
    "value": "SNE",
    "label": "SNE"
  },
  {
    "value": "FTM",
    "label": "FTM"
  },
  {
    "value": "CRV",
    "label": "CRV"
  },
  {
    "value": "TCP",
    "label": "TCP"
  },
  {
    "value": "USDC",
    "label": "USDC"
  },
  {
    "value": "FXS",
    "label": "FXS"
  },
  {
    "value": "FRAX",
    "label": "FRAX"
  },
  {
    "value": "Krill",
    "label": "Krill"
  },
  {
    "value": "USDC",
    "label": "USDC"
  },
  {
    "value": "EROWAN",
    "label": "EROWAN"
  },
  {
    "value": "XPRT",
    "label": "XPRT"
  },
  {
    "value": "PHX",
    "label": "PHX"
  },
  {
    "value": "COMBO",
    "label": "COMBO"
  },
  {
    "value": "DES",
    "label": "DES"
  },
  {
    "value": "USDC",
    "label": "USDC"
  },
  {
    "value": "MASK",
    "label": "MASK"
  },
  {
    "value": "PERA",
    "label": "PERA"
  },
  {
    "value": "KNIGHT",
    "label": "KNIGHT"
  },
  {
    "value": "USDC",
    "label": "USDC"
  },
  {
    "value": "BNB",
    "label": "BNB"
  },
  {
    "value": "AVAX",
    "label": "AVAX"
  },
  {
    "value": "UGT",
    "label": "UGT"
  },
  {
    "value": "ANGEL",
    "label": "ANGEL"
  },
  {
    "value": "polyBUNNY",
    "label": "polyBUNNY"
  },
  {
    "value": "DAI",
    "label": "DAI"
  },
  {
    "value": "USDT",
    "label": "USDT"
  },
  {
    "value": "TRADE",
    "label": "TRADE"
  },
  {
    "value": "REVV",
    "label": "REVV"
  },
  {
    "value": "ETHA",
    "label": "ETHA"
  },
  {
    "value": "QUICK",
    "label": "QUICK"
  },
  {
    "value": "polyBUNNY",
    "label": "polyBUNNY"
  },
  {
    "value": "UGT",
    "label": "UGT"
  },
  {
    "value": "$DG",
    "label": "$DG"
  },
  {
    "value": "UFI",
    "label": "UFI"
  },
  {
    "value": "DAI",
    "label": "DAI"
  },
  {
    "value": "GNS",
    "label": "GNS"
  },
  {
    "value": "JRT",
    "label": "JRT"
  },
  {
    "value": "POOL",
    "label": "POOL"
  },
  {
    "value": "MCASH",
    "label": "MCASH"
  },
  {
    "value": "MEEB",
    "label": "MEEB"
  },
  {
    "value": "WETH",
    "label": "WETH"
  },
  {
    "value": "OM",
    "label": "OM"
  },
  {
    "value": "REI",
    "label": "REI"
  },
  {
    "value": "D11",
    "label": "D11"
  },
  {
    "value": "UCO",
    "label": "UCO"
  },
  {
    "value": "PLR",
    "label": "PLR"
  },
  {
    "value": "ELET",
    "label": "ELET"
  },
  {
    "value": "RAMP",
    "label": "RAMP"
  },
  {
    "value": "RELAY",
    "label": "RELAY"
  },
  {
    "value": "EROWAN",
    "label": "EROWAN"
  },
  {
    "value": "AKT",
    "label": "AKT"
  },
  {
    "value": "UMA",
    "label": "UMA"
  },
  {
    "value": "WMATIC",
    "label": "WMATIC"
  },
  {
    "value": "GHST",
    "label": "GHST"
  },
  {
    "value": "MVI",
    "label": "MVI"
  },
  {
    "value": "ATOM",
    "label": "ATOM"
  },
  {
    "value": "EROWAN",
    "label": "EROWAN"
  },
  {
    "value": "ATOM",
    "label": "ATOM"
  },
  {
    "value": "ALN",
    "label": "ALN"
  },
  {
    "value": "SWAP",
    "label": "SWAP"
  },
  {
    "value": "SAND",
    "label": "SAND"
  },
  {
    "value": "WATCH",
    "label": "WATCH"
  },
  {
    "value": "POOL",
    "label": "POOL"
  },
  {
    "value": "IMX",
    "label": "IMX"
  },
  {
    "value": "START",
    "label": "START"
  },
  {
    "value": "FOX",
    "label": "FOX"
  },
  {
    "value": "USDC",
    "label": "USDC"
  },
  {
    "value": "XCAD",
    "label": "XCAD"
  },
  {
    "value": "ELON",
    "label": "ELON"
  },
  {
    "value": "AXS",
    "label": "AXS"
  },
  {
    "value": "MOONED",
    "label": "MOONED"
  },
  {
    "value": "bct",
    "label": "BCT"
  },
  {
    "value": "klima",
    "label": "KLIMA"
  },
  {
    "value": "pzug",
    "label": "pZUG"
  },
  {
    "value": "gohm",
    "label": "gOHM"
  }
]